pydantic_ast-0.2.0.dist-info/METADATA
pydantic_ast-0.2.0.dist-info/WHEEL
pydantic_ast-0.2.0.dist-info/entry_points.txt
pydantic_ast-0.2.0.dist-info/licenses/LICENSE.txt
pydantic_ast/__init__.py
pydantic_ast/_helpers/_converter.py
pydantic_ast/_nodes/.pytest_cache/.gitignore
pydantic_ast/_nodes/.pytest_cache/CACHEDIR.TAG
pydantic_ast/_nodes/.pytest_cache/README.md
pydantic_ast/_nodes/.pytest_cache/v/cache/nodeids
pydantic_ast/_nodes/.pytest_cache/v/cache/stepwise
pydantic_ast/_nodes/TODO.md
pydantic_ast/_nodes/__init__.py
pydantic_ast/_nodes/_async_and_await.py
pydantic_ast/_nodes/_base.py
pydantic_ast/_nodes/_control_flow.py
pydantic_ast/_nodes/_expr/__init__.py
pydantic_ast/_nodes/_expr/comprehensions.py
pydantic_ast/_nodes/_expr/core.py
pydantic_ast/_nodes/_expr/subscripting.py
pydantic_ast/_nodes/_function_and_classdefs.py
pydantic_ast/_nodes/_literals.py
pydantic_ast/_nodes/_pattern_matching.py
pydantic_ast/_nodes/_root.py
pydantic_ast/_nodes/_statements/__init__.py
pydantic_ast/_nodes/_statements/core.py
pydantic_ast/_nodes/_statements/imports.py
pydantic_ast/_nodes/_variables.py
pydantic_ast/cli.py
pydantic_ast-0.2.0.dist-info/RECORD
